{
  "pools": [
    {
      "name": "main",
      "rolls": 1,
      "entries": [
        {
          "type": "item",
          "name": "harvestfestival:materials",
          "entryName": "agate",
          "weight": 150,
          "functions": [
            {
              "function": "hf_set_enum",
              "enum": "agate"
            }
          ],
          "conditions": [
            {
              "condition": "harvestfestival:between",
              "from": 1,
              "to": 50
            }
          ]
        },
        {
          "type": "item",
          "name": "harvestfestival:materials",
          "entryName": "amethyst",
          "weight": 180,
          "functions": [
            {
              "function": "hf_set_enum",
              "enum": "amethyst"
            }
          ],
          "conditions": [
            {
              "condition": "harvestfestival:between",
              "from": 1,
              "to": 40
            }
          ]
        },
        {
          "type": "item",
          "name": "harvestfestival:materials",
          "entryName": "fluorite",
          "weight": 170,
          "functions": [
            {
              "function": "hf_set_enum",
              "enum": "fluorite"
            }
          ],
          "conditions": [
            {
              "condition": "harvestfestival:between",
              "from": 10,
              "to": 60
            }
          ]
        },
        {
          "type": "item",
          "name": "harvestfestival:materials",
          "entryName": "peridot",
          "weight": 150,
          "functions": [
            {
              "function": "hf_set_enum",
              "enum": "peridot"
            }
          ],
          "conditions": [
            {
              "condition": "harvestfestival:between",
              "from": 20,
              "to": 70
            }
          ]
        },
        {
          "type": "item",
          "name": "harvestfestival:materials",
          "entryName": "ruby",
          "weight": 180,
          "functions": [
            {
              "function": "hf_set_enum",
              "enum": "ruby"
            }
          ],
          "conditions": [
            {
              "condition": "harvestfestival:between",
              "from": 40,
              "to": 100
            }
          ]
        },
        {
          "type": "item",
          "name": "harvestfestival:materials",
          "entryName": "topaz",
          "weight": 120,
          "functions": [
            {
              "function": "hf_set_enum",
              "enum": "peridot"
            }
          ],
          "conditions": [
            {
              "condition": "harvestfestival:between",
              "from": 30,
              "to": 80
            }
          ]
        },
        {
          "type": "item",
          "name": "harvestfestival:materials",
          "entryName": "alexandrite",
          "weight": 10,
          "functions": [
            {
              "function": "hf_set_enum",
              "enum": "alexandrite"
            }
          ],
          "conditions": [
            {
              "condition": "harvestfestival:multiple",
              "of": 10
            },
            {
              "condition": "harvestfestival:from",
              "from": 101
            }
          ]
        },
        {
          "type": "item",
          "name": "minecraft:diamond",
          "entryName": "diamond",
          "weight": 110,
          "conditions": [
            {
              "condition": "harvestfestival:multiple",
              "of": 3
            },
            {
              "condition": "harvestfestival:from",
              "from": 80
            }
          ]
        },
        {
          "type": "item",
          "name": "minecraft:emerald",
          "entryName": "emerald",
          "weight": 145,
          "conditions": [
            {
              "condition": "harvestfestival:between",
              "from": 50,
              "to": 100
            }
          ]
        },
        {
          "type": "item",
          "name": "harvestfestival:materials",
          "entryName": "moon_stone",
          "weight": 200,
          "functions": [
            {
              "function": "hf_set_enum",
              "enum": "moon_stone"
            }
          ],
          "conditions": [
            {
              "condition": "harvestfestival:between",
              "from": 70,
              "to": 100
            }
          ]
        },
        {
          "type": "item",
          "name": "harvestfestival:materials",
          "entryName": "sand_rose",
          "weight": 180,
          "functions": [
            {
              "function": "hf_set_enum",
              "enum": "sand_rose"
            }
          ],
          "conditions": [
            {
              "condition": "harvestfestival:between",
              "from": 60,
              "to": 100
            }
          ]
        },
        {
          "type": "item",
          "name": "harvestfestival:materials",
          "entryName": "pink_diamond",
          "weight": 10,
          "functions": [
            {
              "function": "hf_set_enum",
              "enum": "pink_diamond"
            }
          ],
          "conditions": [
            {
              "condition": "harvestfestival:from",
              "from": 101
            },
            {
              "condition": "harvestfestival:multiple",
              "of": 3
            }
          ]
        }
      ]
    }
  ]
}