{
    "parent": "block/block",
    "textures": {
        "particle": "harvestfestival:models/plate",
        "texture": "harvestfestival:models/plate"
	},
	"elements": [
		{
			"name": "base",
			"from": [5, 0, 5],
			"to": [11, 1, 11],
			"faces": {
				"north": {"uv": [0, 0, 6, 1], "texture": "#texture"},
				"east": {"uv": [0, 0, 6, 1], "texture": "#texture"},
				"south": {"uv": [0, 0, 6, 1], "texture": "#texture"},
				"west": {"uv": [0, 0, 6, 1], "texture": "#texture"},
				"up": {"uv": [10, 10, 16, 16], "texture": "#texture"},
				"down": {"uv": [10, 10, 16, 16], "texture": "#texture"}
			}
		},
		{
			"name": "rim1",
			"from": [5, 0.5, 4],
			"to": [11, 1.5, 5],
			"faces": {
				"north": {"uv": [0, 0, 6, 1], "texture": "#texture"},
				"east": {"uv": [0, 0, 1, 1], "texture": "#texture"},
				"south": {"uv": [0, 0, 6, 1], "texture": "#texture"},
				"west": {"uv": [0, 0, 1, 1], "texture": "#texture"},
				"up": {"uv": [0, 0, 6, 1], "texture": "#texture"},
				"down": {"uv": [0, 0, 6, 1], "texture": "#texture"}
			}
		},
		{
			"name": "rim2",
			"from": [5, 0.5, 11],
			"to": [11, 1.5, 12],
			"faces": {
				"north": {"uv": [0, 0, 6, 1], "texture": "#texture"},
				"east": {"uv": [0, 0, 1, 1], "texture": "#texture"},
				"south": {"uv": [0, 0, 6, 1], "texture": "#texture"},
				"west": {"uv": [0, 0, 1, 1], "texture": "#texture"},
				"up": {"uv": [0, 0, 6, 1], "texture": "#texture"},
				"down": {"uv": [0, 0, 6, 1], "texture": "#texture"}
			}
		},
		{
			"name": "rim3",
			"from": [4, 0.5, 5],
			"to": [5, 1.5, 11],
			"faces": {
				"north": {"uv": [0, 0, 1, 1], "texture": "#texture"},
				"east": {"uv": [0, 0, 6, 1], "texture": "#texture"},
				"south": {"uv": [0, 0, 1, 1], "texture": "#texture"},
				"west": {"uv": [0, 0, 6, 1], "texture": "#texture"},
				"up": {"uv": [0, 0, 1, 6], "texture": "#texture"},
				"down": {"uv": [0, 0, 1, 6], "texture": "#texture"}
			}
		},
		{
			"name": "rim4",
			"from": [11, 0.5, 5],
			"to": [12, 1.5, 11],
			"faces": {
				"north": {"uv": [0, 0, 1, 1], "texture": "#texture"},
				"east": {"uv": [0, 0, 6, 1], "texture": "#texture"},
				"south": {"uv": [0, 0, 1, 1], "texture": "#texture"},
				"west": {"uv": [0, 0, 6, 1], "texture": "#texture"},
				"up": {"uv": [0, 0, 1, 6], "texture": "#texture"},
				"down": {"uv": [0, 0, 1, 6], "texture": "#texture"}
			}
		}
	]
}