{
  "variants": {
    "cookware=frying_pan,facing=north":  { "model": "gastronomy:frying_pan" },
    "cookware=frying_pan,facing=south":  { "model": "gastronomy:frying_pan", "y": 180 },
    "cookware=frying_pan,facing=east": { "model": "gastronomy:frying_pan", "y": 90 },
    "cookware=frying_pan,facing=west": { "model": "gastronomy:frying_pan", "y": 270 },
    "cookware=mixer,facing=north":  { "model": "gastronomy:mixer" },
    "cookware=mixer,facing=south":  { "model": "gastronomy:mixer", "y": 180 },
    "cookware=mixer,facing=east": { "model": "gastronomy:mixer", "y": 90 },
    "cookware=mixer,facing=west": { "model": "gastronomy:mixer", "y": 270 },
    "cookware=oven_off,facing=north":  { "model": "gastronomy:oven_off" },
    "cookware=oven_off,facing=south":  { "model": "gastronomy:oven_off", "y": 180 },
    "cookware=oven_off,facing=east": { "model": "gastronomy:oven_off", "y": 90 },
    "cookware=oven_off,facing=west": { "model": "gastronomy:oven_off", "y": 270 },
    "cookware=pot,facing=north":  { "model": "gastronomy:pot" },
    "cookware=pot,facing=south":  { "model": "gastronomy:pot", "y": 180 },
    "cookware=pot,facing=east": { "model": "gastronomy:pot", "y": 90 },
    "cookware=pot,facing=west": { "model": "gastronomy:pot", "y": 270 },
    "cookware=counter,facing=north":  { "model": "gastronomy:counter" },
    "cookware=counter,facing=south":  { "model": "gastronomy:counter", "y": 180 },
    "cookware=counter,facing=east": { "model": "gastronomy:counter", "y": 90 },
    "cookware=counter,facing=west": { "model": "gastronomy:counter", "y": 270 },
    "cookware=counter_oc,facing=north":  { "model": "gastronomy:counter_outer" },
    "cookware=counter_oc,facing=south":  { "model": "gastronomy:counter_outer", "y": 180 },
    "cookware=counter_oc,facing=east": { "model": "gastronomy:counter_outer", "y": 90 },
    "cookware=counter_oc,facing=west": { "model": "gastronomy:counter_outer", "y": 270 },
    "cookware=counter_ic,facing=north":  { "model": "gastronomy:counter_inner" },
    "cookware=counter_ic,facing=south":  { "model": "gastronomy:counter_inner", "y": 180 },
    "cookware=counter_ic,facing=east": { "model": "gastronomy:counter_inner", "y": 90 },
    "cookware=counter_ic,facing=west": { "model": "gastronomy:counter_inner", "y": 270 },
    "cookware=oven_on,facing=north":  { "model": "gastronomy:oven_on" },
    "cookware=oven_on,facing=south":  { "model": "gastronomy:oven_on", "y": 180 },
    "cookware=oven_on,facing=east": { "model": "gastronomy:oven_on", "y": 90 },
    "cookware=oven_on,facing=west": { "model": "gastronomy:oven_on", "y": 270 },
    "cookware=island,facing=north":  { "model": "gastronomy:island" },
    "cookware=island,facing=south":  { "model": "gastronomy:island", "y": 180 },
    "cookware=island,facing=east": { "model": "gastronomy:island", "y": 90 },
    "cookware=island,facing=west": { "model": "gastronomy:island", "y": 270 },
    "cookware=island_oc,facing=north":  { "model": "gastronomy:island_outer" },
    "cookware=island_oc,facing=south":  { "model": "gastronomy:island_outer", "y": 180 },
    "cookware=island_oc,facing=east": { "model": "gastronomy:island_outer", "y": 90 },
    "cookware=island_oc,facing=west": { "model": "gastronomy:island_outer", "y": 270 },
    "cookware=island_ic,facing=north":  { "model": "gastronomy:island_inner" },
    "cookware=island_ic,facing=south":  { "model": "gastronomy:island_inner", "y": 180 },
    "cookware=island_ic,facing=east": { "model": "gastronomy:island_inner", "y": 90 },
    "cookware=island_ic,facing=west": { "model": "gastronomy:island_inner", "y": 270 },
    "cookware=sink,facing=north":  { "model": "gastronomy:sink" },
    "cookware=sink,facing=south":  { "model": "gastronomy:sink", "y": 180 },
    "cookware=sink,facing=east": { "model": "gastronomy:sink", "y": 90 },
    "cookware=sink,facing=west": { "model": "gastronomy:sink", "y": 270 },
    "inventory_oven": { "model": "gastronomy:oven_inventory" }
  }
}