{
  "variants": {
    "facing=north,questblock=board":  { "model": "harvestfestival:quest_block" },
    "facing=south,questblock=board":  { "model": "harvestfestival:quest_block", "y": 180 },
    "facing=east,questblock=board": { "model": "harvestfestival:quest_block", "y": 90 },
    "facing=west,questblock=board": { "model": "harvestfestival:quest_block", "y": 270 },
    "facing=north,questblock=active":  { "model": "harvestfestival:quest_block_active" },
    "facing=south,questblock=active":  { "model": "harvestfestival:quest_block_active", "y": 180 },
    "facing=east,questblock=active": { "model": "harvestfestival:quest_block_active", "y": 90 },
    "facing=west,questblock=active": { "model": "harvestfestival:quest_block_active", "y": 270 }
  }
}