{
  "pools": [
    {
      "name": "barn",
      "rolls": 1,
      "entries": [
        {
          "type": "item",
          "name": "minecraft:wheat",
          "weight": 10
        },
        {
          "type": "item",
          "name": "minecraft:carrot",
          "weight": 10
        },
        {
          "type": "item",
          "name": "minecraft:lead",
          "weight": 8
        },
        {
          "type": "item",
          "name": "minecraft:carrot_on_a_stick",
          "weight": 1
        },
        {
          "type": "item",
          "name": "harvestfestival:tool_animal",
          "entryName": "brush",
          "weight": 3,
          "functions": [
            {
              "function": "hf_set_enum",
              "enum": "brush"
            }
          ]
        },
        {
          "type": "item",
          "name": "harvestfestival:tool_animal",
          "entryName": "medicine",
          "weight": 1,
          "functions": [
            {
              "function": "hf_set_enum",
              "enum": "medicine"
            }
          ]
        },
        {
          "type": "item",
          "name": "harvestfestival:crops",
          "weight": 6,
          "functions": [
            {
              "function": "hf_set_crop",
              "crop": "grass"
            }
          ]
        }
      ]
    }
  ]
}