{
  "pools": [
    {
      "name": "blacksmith",
      "rolls": 3,
      "entries": [
        {
          "type": "item",
          "name": "minecraft:iron_ingot",
          "weight": 4,
          "functions": [
            {
              "function": "set_count",
              "count": {
                "min": 2,
                "max": 5
              }
            }
          ]
        },
        {
          "type": "item",
          "name": "minecraft:lava_bucket",
          "weight": 2,
          "functions": [
            {
              "function": "set_count",
              "count": {
                "min": 1,
                "max": 2
              }
            }
          ]
        },
        {
          "type": "item",
          "name": "minecraft:coal",
          "weight": 6,
          "functions": [
            {
              "function": "set_count",
              "count": {
                "min": 3,
                "max": 33
              }
            }
          ]
        },
        {
          "type": "item",
          "name": "minecraft:leather",
          "weight": 10,
          "functions": [
            {
              "function": "set_count",
              "count": {
                "min": 13,
                "max": 64
              }
            }
          ]
        }
      ]
    }
  ]
}